main.py
mseep_outlookmcpserver-0.1.2.dist-info/licenses/LICENSE
mseep_outlookmcpserver-0.1.2.dist-info/METADATA
mseep_outlookmcpserver-0.1.2.dist-info/WHEEL
mseep_outlookmcpserver-0.1.2.dist-info/entry_points.txt
mseep_outlookmcpserver-0.1.2.dist-info/top_level.txt
mseep_outlookmcpserver-0.1.2.dist-info/RECORD
